graphgallery/__init__.py
graphgallery/data_type.py
graphgallery/sampler.cp37-win_amd64.pyd
graphgallery/version.py
graphgallery/attack/__init__.py
graphgallery/attack/attacker.py
graphgallery/attack/flip_attacker.py
graphgallery/attack/backdoor/__init__.py
graphgallery/attack/targeted/__init__.py
graphgallery/attack/targeted/registered_models.py
graphgallery/attack/targeted/targeted_attacker.py
graphgallery/attack/targeted/common/__init__.py
graphgallery/attack/targeted/common/dice.py
graphgallery/attack/targeted/common/gf_attack.py
graphgallery/attack/targeted/common/nettack.py
graphgallery/attack/targeted/common/node_embedding_attack.py
graphgallery/attack/targeted/common/rand.py
graphgallery/attack/targeted/pytorch/__init__.py
graphgallery/attack/targeted/pytorch/sga.py
graphgallery/attack/targeted/tensorflow/__init__.py
graphgallery/attack/targeted/tensorflow/faster_sga.py
graphgallery/attack/targeted/tensorflow/fgsm.py
graphgallery/attack/targeted/tensorflow/integrated_gradient_attack.py
graphgallery/attack/targeted/tensorflow/iterative_gradient_attack.py
graphgallery/attack/targeted/tensorflow/sga.py
graphgallery/attack/untargeted/__init__.py
graphgallery/attack/untargeted/registered_models.py
graphgallery/attack/untargeted/untargeted_attacker.py
graphgallery/attack/untargeted/common/__init__.py
graphgallery/attack/untargeted/common/degree.py
graphgallery/attack/untargeted/common/dice.py
graphgallery/attack/untargeted/common/node_embedding_attack.py
graphgallery/attack/untargeted/common/rand.py
graphgallery/attack/untargeted/pytorch/__init__.py
graphgallery/attack/untargeted/pytorch/metattack.py
graphgallery/attack/untargeted/pytorch/pgd.py
graphgallery/attack/untargeted/tensorflow/__init__.py
graphgallery/attack/untargeted/tensorflow/fgsm.py
graphgallery/attack/untargeted/tensorflow/metattack.py
graphgallery/attack/untargeted/tensorflow/pgd.py
graphgallery/attack/untargeted/tensorflow/experimental/__init__.py
graphgallery-1.0.0.dist-info/LICENSE
graphgallery-1.0.0.dist-info/METADATA
graphgallery-1.0.0.dist-info/WHEEL
graphgallery-1.0.0.dist-info/top_level.txt
graphgallery-1.0.0.dist-info/RECORD
