Metadata-Version: 2.1
Name: graphgallery
Version: 1.0.0
Summary: A Gallery for Benchmarking Graph Neural Networks and Graph Adversarial Learning.
Home-page: https://github.com/EdisonLeeeee/GraphGallery
Author: Jintang Li
Author-email: lijt55@mail2.sysu.edu.cn
License: MIT LICENSE
Download-URL: https://github.com/EdisonLeeeee/GraphGallery/archive/1.0.0.tar.gz
Keywords: tensorflow,pytorch,benchmark,geometric-deep-learning,graph-neural-networks
Platform: UNKNOWN
Classifier: Development Status :: 3 - Alpha
Classifier: Intended Audience :: Science/Research
Classifier: License :: OSI Approved :: MIT License
Classifier: Topic :: Scientific/Engineering :: Artificial Intelligence
Classifier: Topic :: Scientific/Engineering
Classifier: Topic :: Software Development :: Libraries
Classifier: Operating System :: Microsoft :: Windows
Classifier: Operating System :: Unix
Classifier: Programming Language :: Python :: 3
Classifier: Programming Language :: Python :: 3.6
Classifier: Programming Language :: Python :: 3.7
Classifier: Programming Language :: Python :: 3.8
Requires-Python: >=3.6
License-File: LICENSE
Requires-Dist: tqdm
Requires-Dist: yacs
Requires-Dist: scipy
Requires-Dist: numpy
Requires-Dist: tabulate
Requires-Dist: pandas
Requires-Dist: scikit-learn (>=0.21.0)
Requires-Dist: networkx (>=2.3)
Requires-Dist: gensim (>=3.8.0)
Requires-Dist: numba (>=0.46.0)
Provides-Extra: test
Requires-Dist: pytest ; extra == 'test'
Requires-Dist: pytest-cov ; extra == 'test'
